artscraper/__init__.py
artscraper/base.py
artscraper/find_artists.py
artscraper/find_artworks.py
artscraper/functions.py
artscraper/googleart.py
artscraper/wikiart.py
artscraper-0.3.1.dist-info/LICENSE
artscraper-0.3.1.dist-info/METADATA
artscraper-0.3.1.dist-info/WHEEL
artscraper-0.3.1.dist-info/top_level.txt
artscraper-0.3.1.dist-info/RECORD
