Metadata-Version: 2.1
Name: artscraper
Version: 0.3.1
Summary: Package for scraping artworks from WikiArt and GoogleArt
Home-page: https://github.com/sodascience/artscraper
Author: ODISSEI Social Data Science Team
License: MIT
Keywords: artscraper wikiart artsandculture
Requires-Python: ~=3.6
License-File: LICENSE
Requires-Dist: requests
Requires-Dist: selenium
Requires-Dist: beautifulsoup4
Requires-Dist: wikipedia-api
Requires-Dist: webdriver-manager
